{
    "dependencies": {
    },
    "replacing": {
    },
    "description": "Configures /etc/resolv.conf",
    "groupings": {
    },
    "platforms": {
      "freebsd": [

      ],
      "ubuntu": [

      ],
      "openbsd": [

      ],
      "fedora": [

      ],
      "macosx": [

      ],
      "centos": [

      ],
      "redhat": [

      ],
      "debian": [

      ]
    },
    "version": "0.7.0",
    "recommendations": {
    },
    "name": "resolver",
    "maintainer": "Opscode, Inc.",
    "long_description": "",
    "recipes": {
    },
    "suggestions": {
    },
    "maintainer_email": "cookbooks@opscode.com",
    "attributes": {
      "resolver/nameservers": {
        "calculated": false,
        "default": [
          ""
        ],
        "type": "array",
        "choice": [

        ],
        "description": "Default nameservers",
        "display_name": "Resolver Nameservers",
        "recipes": [

        ],
        "required": "optional"
      },
      "resolver": {
        "calculated": false,
        "type": "hash",
        "choice": [

        ],
        "description": "Hash of Resolver attributes",
        "display_name": "Resolver",
        "recipes": [

        ],
        "required": "optional"
      },
      "resolver/search": {
        "calculated": false,
        "default": "domain",
        "type": "string",
        "choice": [

        ],
        "description": "Default domain to search",
        "display_name": "Resolver Search",
        "recipes": [

        ],
        "required": "optional"
      }
    },
    "conflicting": {
    },
    "license": "Apache 2.0",
    "providing": {
    }
  }