{
    "recommendations": {
    },
    "attributes": {
    },
    "maintainer": "Opscode, Inc.",
    "suggestions": {
    },
    "dependencies": {
    },
    "maintainer_email": "cookbooks@opscode.com",
    "conflicting": {
    },
    "platforms": {
      "debian": [

      ],
      "ubuntu": [

      ]
    },
    "license": "Apache 2.0",
    "version": "0.7.0",
    "providing": {
    },
    "recipes": {
      "python": "Installs python and common python module packages"
    },
    "replacing": {
    },
    "name": "python",
    "description": "Installs python packages",
    "groupings": {
    },
    "long_description": ""
  }