{
    "dependencies": {
    },
    "replacing": {
    },
    "description": "Installs emacs",
    "groupings": {
    },
    "platforms": {
      "ubuntu": [

      ],
      "centos": [

      ],
      "redhat": [

      ],
      "debian": [

      ]
    },
    "version": "0.7.0",
    "recommendations": {
    },
    "name": "emacs",
    "maintainer": "Opscode, Inc.",
    "long_description": "",
    "recipes": {
    },
    "suggestions": {
    },
    "maintainer_email": "cookbooks@opscode.com",
    "attributes": {
    },
    "conflicting": {
    },
    "license": "Apache 2.0",
    "providing": {
    }
  }