{
    "maintainer": "Opscode, Inc.",
    "attributes": {
      "packages": {
        "calculated": false,
        "type": "hash",
        "choice": [

        ],
        "description": "Hash of Packages attributes",
        "display_name": "Packages",
        "required": "optional",
        "recipes": [

        ]
      },
      "packages/dist_only": {
        "default": "false",
        "calculated": false,
        "type": "string",
        "choice": [

        ],
        "description": "Set to only use distribution-provided packages",
        "display_name": "Packages Distribution Only?",
        "required": "optional",
        "recipes": [

        ]
      }
    },
    "suggestions": {
    },
    "platforms": {
      "centos": [

      ],
      "redhat": [

      ]
    },
    "dependencies": {
    },
    "maintainer_email": "cookbooks@opscode.com",
    "conflicting": {
    },
    "version": "0.9.0",
    "name": "packages",
    "recipes": {
    },
    "providing": {
    },
    "license": "Apache 2.0",
    "replacing": {
    },
    "groupings": {
    },
    "long_description": "",
    "recommendations": {
    },
    "description": "Helper library to determine whether distribution-only packages are installed"
  }